LICENSE
requirements-gpu.txt
requirements.txt
setup.py
deepr/__init__.py
deepr/version.py
deepr.egg-info/PKG-INFO
deepr.egg-info/SOURCES.txt
deepr.egg-info/dependency_links.txt
deepr.egg-info/entry_points.txt
deepr.egg-info/requires.txt
deepr.egg-info/top_level.txt
deepr/cli/__init__.py
deepr/cli/main.py
deepr/config/__init__.py
deepr/config/base.py
deepr/config/experimental.py
deepr/config/macros.py
deepr/config/references.py
deepr/examples/__init__.py
deepr/examples/movielens/__init__.py
deepr/examples/movielens/jobs/__init__.py
deepr/examples/movielens/jobs/build_records.py
deepr/examples/movielens/jobs/evaluate.py
deepr/examples/movielens/jobs/init.py
deepr/examples/movielens/jobs/predict.py
deepr/examples/movielens/jobs/svd.py
deepr/examples/movielens/layers/__init__.py
deepr/examples/movielens/layers/average.py
deepr/examples/movielens/layers/bpr.py
deepr/examples/movielens/layers/losses.py
deepr/examples/movielens/layers/multi.py
deepr/examples/movielens/layers/ns.py
deepr/examples/movielens/layers/transformer.py
deepr/examples/movielens/layers/vae.py
deepr/examples/movielens/macros/__init__.py
deepr/examples/movielens/macros/paths.py
deepr/examples/movielens/metrics/__init__.py
deepr/examples/movielens/metrics/ndcg.py
deepr/examples/movielens/metrics/recall.py
deepr/examples/movielens/prepros/__init__.py
deepr/examples/movielens/prepros/csv.py
deepr/examples/movielens/prepros/record.py
deepr/examples/movielens/readers/__init__.py
deepr/examples/movielens/readers/csv.py
deepr/examples/movielens/utils/__init__.py
deepr/examples/movielens/utils/fields.py
deepr/examples/multiply/__init__.py
deepr/examples/multiply/jobs/__init__.py
deepr/examples/multiply/jobs/build.py
deepr/examples/multiply/jobs/predict.py
deepr/examples/multiply/layers/__init__.py
deepr/examples/multiply/layers/loss.py
deepr/examples/multiply/layers/model.py
deepr/examples/multiply/macros/__init__.py
deepr/examples/multiply/macros/paths.py
deepr/examples/multiply/prepros/__init__.py
deepr/examples/multiply/prepros/default.py
deepr/examples/multiply/prepros/inference.py
deepr/exporters/__init__.py
deepr/exporters/base.py
deepr/exporters/best_checkpoint.py
