Metadata-Version: 2.1
Name: deepr
Version: 2.13.0
Summary: DeepR: Build and Train Deep Learning Pipelines for Production
Home-page: UNKNOWN
Author: Criteo
License: UNKNOWN
Platform: UNKNOWN
Classifier: License :: OSI Approved :: Apache Software License
Classifier: Operating System :: OS Independent
Classifier: Programming Language :: Python :: 3
Classifier: Programming Language :: Python :: 3.6
Classifier: Intended Audience :: Developers
Classifier: Intended Audience :: Science/Research
Classifier: Development Status :: 5 - Production/Stable
Classifier: Topic :: Scientific/Engineering :: Artificial Intelligence
Provides-Extra: cpu
Provides-Extra: gpu
License-File: LICENSE
